tw2.fontawesome-4.7.0-py3.7-nspkg.pth
tw2/fontawesome/__init__.py
tw2/fontawesome/config.py
tw2/fontawesome/metadata.py
tw2/fontawesome/resources.py
tw2/fontawesome/widgets.py
tw2/fontawesome/static/css/font-awesome.css
tw2/fontawesome/static/css/font-awesome.min.css
tw2/fontawesome/static/fonts/fontawesome-webfont.eot
tw2/fontawesome/static/fonts/fontawesome-webfont.ttf
tw2/fontawesome/static/fonts/fontawesome-webfont.woff
tw2/fontawesome/static/fonts/fontawesome-webfont.woff2
tw2.fontawesome-4.7.0.dist-info/METADATA
tw2.fontawesome-4.7.0.dist-info/WHEEL
tw2.fontawesome-4.7.0.dist-info/entry_points.txt
tw2.fontawesome-4.7.0.dist-info/namespace_packages.txt
tw2.fontawesome-4.7.0.dist-info/top_level.txt
tw2.fontawesome-4.7.0.dist-info/RECORD
